pyrdfsubset/__init__.py
pyrdfsubset/__main__.py
pyrdfsubset/rdfsubset.py
pyrdfsubset/sparqlsubset.py
pyrdfsubset-0.1.3.dist-info/LICENSE
pyrdfsubset-0.1.3.dist-info/METADATA
pyrdfsubset-0.1.3.dist-info/WHEEL
pyrdfsubset-0.1.3.dist-info/entry_points.txt
pyrdfsubset-0.1.3.dist-info/top_level.txt
pyrdfsubset-0.1.3.dist-info/RECORD
