Metadata-Version: 2.1
Name: pyrdfsubset
Version: 0.1.3
Summary: Create RDF subsets based on ShEx constraints and optionally SPARQL query results. The development of this library started at the Biohackathon Japan in 2023 in Shodoshima
Author-email: Andra Waagmeester <andra@micelio.be>
License: MIT License
Project-URL: Homepage, https://github.com/micelio/PyRDFSubSet
Keywords: shex,rdf,subsets,biohackathon
Classifier: License :: OSI Approved :: MIT License
Classifier: Programming Language :: Python
Classifier: Programming Language :: Python :: 3
Requires-Python: >=3.8
License-File: LICENSE
Requires-Dist: rdflib
Requires-Dist: pyshex
